django_zipkin_trace-1.0.2.dist-info/METADATA
django_zipkin_trace-1.0.2.dist-info/RECORD
django_zipkin_trace-1.0.2.dist-info/WHEEL
django_zipkin_trace-1.0.2.dist-info/top_level.txt
zipkin_trace/__init__.py
zipkin_trace/db_tracing.py
zipkin_trace/middleware.py
zipkin_trace/monkey_patch.py
zipkin_trace/template_tracing.py
zipkin_trace/urllib3_tracing.py
zipkin_trace/utils.py
