Metadata-Version: 2.1
Name: django-zipkin-trace
Version: 1.0.2
Summary: Automatically trace your Django application to Zipkin
Home-page: https://github.com/whs/django-zipkin-trace
Author: Manatsawin Hanmongkolchai
Author-email: manatsawin+pypi@gmail.com
License: MIT
Platform: UNKNOWN
Classifier: Development Status :: 5 - Production/Stable
Classifier: Environment :: Web Environment
Classifier: Framework :: Django
Classifier: Intended Audience :: Developers
Classifier: License :: OSI Approved :: MIT License
Classifier: Operating System :: OS Independent
Classifier: Programming Language :: Python
Classifier: Programming Language :: Python :: 3
Classifier: Programming Language :: Python :: 3 :: Only
Classifier: Programming Language :: Python :: 3.4
Classifier: Programming Language :: Python :: 3.5
Classifier: Programming Language :: Python :: 3.6
Classifier: Topic :: System :: Networking :: Monitoring
Requires-Dist: Django
Requires-Dist: py-zipkin (==0.11.0)
Requires-Dist: requests-futures (==0.9.7)
